{
  "users": [
    {
      "password": "password1",
      "name":"John Doe",
      "id": "1"
    },
    {
      "id": "2",
      "name": "Jane Smith",
      "password": "password2"
    },
    {
      "id": "3",
      "name": "Alice Johnson",
      "password": "password3"
    }
  ],
  "inquiries": [
    {
      "ID": 874365,
      "Sender": "John Doe",
      "Title": "Urgent Issue",
      "Text": "Need immediate attention",
      "Category": "Technical",
      "Executor": "Alice Smith",
      "Date": "2024-02-22",
      "Status": "Opened",
      "id": "5dd8"
    },
    {
      "ID": 624179,
      "Sender": "Jane Smith",
      "Title": "Feedback",
      "Text": "Positive feedback on recent updates",
      "Category": "Feedback",
      "Executor": "Bob Johnson",
      "Date": "2024-02-21",
      "Status": "Execution",
      "id": "7c5a"
    },
    {
      "ID": 912837,
      "Sender": "Emily Davis",
      "Title": "Bug Report",
      "Text": "Unable to login",
      "Category": "Technical",
      "Executor": "Chris Brown",
      "Date": "2024-02-20",
      "Status": "Closed",
      "id": "c148"
    },
    {
      "ID": 497128,
      "Sender": "Alex Johnson",
      "Title": "Feature Request",
      "Text": "Requesting a new feature",
      "Category": "Feature Request",
      "Executor": "Emma Lee",
      "Date": "2024-02-19",
      "Status": "Hold",
      "id": "f1b7"
    },
    {
      "ID": 231947,
      "Sender": "Michael Wilson",
      "Title": "Complaint",
      "Text": "Experiencing issues with the product",
      "Category": "Customer Support",
      "Executor": "David Brown",
      "Date": "2024-02-18",
      "Status": "Approved",
      "id": "bf77"
    },
    {
      "ID": 812394,
      "Sender": "Sophia Martinez",
      "Title": "Question",
      "Text": "Seeking clarification on a feature",
      "Category": "General Inquiry",
      "Executor": "Olivia Garcia",
      "Date": "2024-02-17",
      "Status": "Refused",
      "id": "bc1d"
    },
    {
      "ID": 481923,
      "Sender": "Sophia Martinez",
      "Title": "Question",
      "Text": "Seeking clarification on a feature",
      "Category": "General Inquiry",
      "Executor": "Olivia Garcia",
      "Date": "2024-02-17",
      "Status": "Refused",
      "id": "8489"
    },
    {
      "ID": 751298,
      "Sender": "Emma Johnson",
      "Title": "Technical Support",
      "Text": "Need help with technical issue",
      "Category": "Technical",
      "Executor": "John Smith",
      "Date": "2024-02-16",
      "Status": "Opened",
      "id": "02a4"
    },
    {
      "ID": 123847,
      "Sender": "David Brown",
      "Title": "New Feature Proposal",
      "Text": "Suggesting a new feature",
      "Category": "Feature Request",
      "Executor": "Michael Wilson",
      "Date": "2024-02-15",
      "Status": "Execution",
      "id": "8f0e"
    },
    {
      "ID": 823749,
      "Sender": "Olivia Garcia",
      "Title": "Login Issue",
      "Text": "Unable to login to the system",
      "Category": "Technical",
      "Executor": "Sophia Martinez",
      "Date": "2024-02-14",
      "Status": "Closed",
      "id": "8178"
    },
    {
      "ID": 571823,
      "Sender": "John Doe",
      "Title": "Product Feedback",
      "Text": "Providing feedback on recent updates",
      "Category": "Feedback",
      "Executor": "Jane Smith",
      "Date": "2024-02-13",
      "Status": "Hold",
      "id": "6ca1"
    },
    {
      "ID": 198273,
      "Sender": "Jane Smith",
      "Title": "Service Complaint",
      "Text": "Unsatisfactory service experience",
      "Category": "Customer Support",
      "Executor": "Alex Johnson",
      "Date": "2024-02-12",
      "Status": "Approved",
      "id": "04fc"
    },
    {
      "ID": 732184,
      "Sender": "Emily Davis",
      "Title": "Feature Query",
      "Text": "Seeking information about a feature",
      "Category": "General Inquiry",
      "Executor": "Michael Wilson",
      "Date": "2024-02-11",
      "Status": "Refused",
      "id": "9b3c"
    },
    {
      "ID": 612349,
      "Sender": "Alex Johnson",
      "Title": "Software Issue",
      "Text": "Encountering technical problem with the software",
      "Category": "Technical",
      "Executor": "David Brown",
      "Date": "2024-02-10",
      "Status": "Opened",
      "id": "d1c4"
    },
    {
      "ID": 192837,
      "Sender": "Michael Wilson",
      "Title": "Feature Addition",
      "Text": "Requesting addition of new feature",
      "Category": "Feature Request",
      "Executor": "John Doe",
      "Date": "2024-02-09",
      "Status": "Execution",
      "id": "fb9e"
    },
    {
      "ID": 123847,
      "Sender": "David Brown",
      "Title": "New Feature Proposal",
      "Text": "Suggesting a new feature",
      "Category": "Feature Request",
      "Executor": "Michael Wilson",
      "Date": "2024-02-15",
      "Status": "Execution",
      "id": "31e6"
    },
    {
      "ID": 123848,
      "Sender": "John Doe",
      "Title": "New Feature Proposal",
      "Text": "Suggesting a new feature",
      "Category": "Feature Request",
      "Executor": "Michael Wilson",
      "Date": "2024-02-15",
      "Status": "Closed",
      "id": "63b5"
    },
    {
      "ID": 123849,
      "Sender": "Jane Smith",
      "Title": "New Feature Proposal",
      "Text": "Suggesting a new feature",
      "Category": "Feature Request",
      "Executor": "Michael Wilson",
      "Date": "2024-02-15",
      "Status": "Refused",
      "id": "afff"
    },
    {
      "ID": 123847,
      "Sender": "David Brown",
      "Title": "New Feature Proposal",
      "Text": "Suggesting a new feature",
      "Category": "Feature Request",
      "Executor": "Michael Wilson",
      "Date": "2024-02-15",
      "Status": "Opened",
      "id": "065c"
    },
    {
      "ID": 123848,
      "Sender": "John Doe",
      "Title": "New Feature Proposal",
      "Text": "Suggesting a new feature",
      "Category": "Feature Request",
      "Executor": "Michael Wilson",
      "Date": "2024-02-15",
      "Status": "Approved",
      "id": "ed89"
    },
    {
      "ID": 874365,
      "Sender": "John Doe",
      "Title": "Urgent Issue",
      "Text": "Need immediate attention",
      "Category": "Technical",
      "Executor": "Alice Smith",
      "Date": "2024-02-22",
      "Status": "Opened",
      "id": "b08e"
    },
    {
      "ID": 624179,
      "Sender": "Jane Smith",
      "Title": "Feedback",
      "Text": "Positive feedback on recent updates",
      "Category": "Feedback",
      "Executor": "Bob Johnson",
      "Date": "2024-02-21",
      "Status": "Execution",
      "id": "de38"
    },
    {
      "ID": 912837,
      "Sender": "Emily Davis",
      "Title": "Bug Report",
      "Text": "Unable to login",
      "Category": "Technical",
      "Executor": "Chris Brown",
      "Date": "2024-02-20",
      "Status": "Closed",
      "id": "f76b"
    },
    {
      "ID": 497128,
      "Sender": "Alex Johnson",
      "Title": "Feature Request",
      "Text": "Requesting a new feature",
      "Category": "Feature Request",
      "Executor": "Emma Lee",
      "Date": "2024-02-19",
      "Status": "Hold",
      "id": "c9bd"
    },
    {
      "ID": 231947,
      "Sender": "Michael Wilson",
      "Title": "Complaint",
      "Text": "Experiencing issues with the product",
      "Category": "Customer Support",
      "Executor": "David Brown",
      "Date": "2024-02-18",
      "Status": "Approved",
      "id": "7ffc"
    },
    {
      "ID": 812394,
      "Sender": "Sophia Martinez",
      "Title": "Question",
      "Text": "Seeking clarification on a feature",
      "Category": "General Inquiry",
      "Executor": "Olivia Garcia",
      "Date": "2024-02-17",
      "Status": "Refused",
      "id": "79b7"
    },
    {
      "ID": 481923,
      "Sender": "Sophia Martinez",
      "Title": "Question",
      "Text": "Seeking clarification on a feature",
      "Category": "General Inquiry",
      "Executor": "Olivia Garcia",
      "Date": "2024-02-17",
      "Status": "Refused",
      "id": "c766"
    },
    {
      "ID": 751298,
      "Sender": "Emma Johnson",
      "Title": "Technical Support",
      "Text": "Need help with technical issue",
      "Category": "Technical",
      "Executor": "John Smith",
      "Date": "2024-02-16",
      "Status": "Opened",
      "id": "8a79"
    },
    {
      "ID": 123847,
      "Sender": "David Brown",
      "Title": "New Feature Proposal",
      "Text": "Suggesting a new feature",
      "Category": "Feature Request",
      "Executor": "Michael Wilson",
      "Date": "2024-02-15",
      "Status": "Execution",
      "id": "b485"
    },
    {
      "ID": 823749,
      "Sender": "Olivia Garcia",
      "Title": "Login Issue",
      "Text": "Unable to login to the system",
      "Category": "Technical",
      "Executor": "Sophia Martinez",
      "Date": "2024-02-14",
      "Status": "Closed",
      "id": "3c5f"
    },
    {
      "ID": 571823,
      "Sender": "John Doe",
      "Title": "Product Feedback",
      "Text": "Providing feedback on recent updates",
      "Category": "Feedback",
      "Executor": "Jane Smith",
      "Date": "2024-02-13",
      "Status": "Hold",
      "id": "864b"
    },
    {
      "ID": 198273,
      "Sender": "Jane Smith",
      "Title": "Service Complaint",
      "Text": "Unsatisfactory service experience",
      "Category": "Customer Support",
      "Executor": "Alex Johnson",
      "Date": "2024-02-12",
      "Status": "Approved",
      "id": "9537"
    },
    {
      "ID": 732184,
      "Sender": "Emily Davis",
      "Title": "Feature Query",
      "Text": "Seeking information about a feature",
      "Category": "General Inquiry",
      "Executor": "Michael Wilson",
      "Date": "2024-02-11",
      "Status": "Refused",
      "id": "3a4f"
    },
    {
      "ID": 612349,
      "Sender": "Alex Johnson",
      "Title": "Software Issue",
      "Text": "Encountering technical problem with the software",
      "Category": "Technical",
      "Executor": "David Brown",
      "Date": "2024-02-10",
      "Status": "Opened",
      "id": "e01a"
    },
    {
      "ID": 192837,
      "Sender": "Michael Wilson",
      "Title": "Feature Addition",
      "Text": "Requesting addition of new feature",
      "Category": "Feature Request",
      "Executor": "John Doe",
      "Date": "2024-02-09",
      "Status": "Execution",
      "id": "46e4"
    },
    {
      "ID": 123847,
      "Sender": "David Brown",
      "Title": "New Feature Proposal",
      "Text": "Suggesting a new feature",
      "Category": "Feature Request",
      "Executor": "Michael Wilson",
      "Date": "2024-02-15",
      "Status": "Execution",
      "id": "8d21"
    },
    {
      "ID": 123848,
      "Sender": "John Doe",
      "Title": "New Feature Proposal",
      "Text": "Suggesting a new feature",
      "Category": "Feature Request",
      "Executor": "Michael Wilson",
      "Date": "2024-02-15",
      "Status": "Closed",
      "id": "98c8"
    },
    {
      "ID": 123849,
      "Sender": "Jane Smith",
      "Title": "New Feature Proposal",
      "Text": "Suggesting a new feature",
      "Category": "Feature Request",
      "Executor": "Michael Wilson",
      "Date": "2024-02-15",
      "Status": "Refused",
      "id": "f0f1"
    },
    {
      "ID": 123847,
      "Sender": "David Brown",
      "Title": "New Feature Proposal",
      "Text": "Suggesting a new feature",
      "Category": "Feature Request",
      "Executor": "Michael Wilson",
      "Date": "2024-02-15",
      "Status": "Opened",
      "id": "f20a"
    },
    {
      "ID": 123848,
      "Sender": "John Doe",
      "Title": "New Feature Proposal",
      "Text": "Suggesting a new feature",
      "Category": "Feature Request",
      "Executor": "Michael Wilson",
      "Date": "2024-02-15",
      "Status": "Approved",
      "id": "d7fe"
    },
    {
      "ID": 123850,
      "Sender": "Alice Brown",
      "Title": "Feature Suggestion",
      "Text": "Proposing a new feature idea",
      "Category": "Feature Request",
      "Executor": "Bob Johnson",
      "Date": "2024-02-15",
      "Status": "Execution",
      "id": "b0bf"
    },
    {
      "ID": 123851,
      "Sender": "Samuel Smith",
      "Title": "Technical Issue",
      "Text": "Experiencing technical difficulties",
      "Category": "Technical",
      "Executor": "Chris Davis",
      "Date": "2024-02-15",
      "Status": "Opened",
      "id": "a696"
    },
    {
      "ID": 123852,
      "Sender": "Emily Wilson",
      "Title": "Feature Request",
      "Text": "Requesting a new feature",
      "Category": "Feature Request",
      "Executor": "David Brown",
      "Date": "2024-02-15",
      "Status": "Hold",
      "id": "7f89"
    },
    {
      "ID": 123853,
      "Sender": "John Smith",
      "Title": "Product Feedback",
      "Text": "Providing feedback on recent updates",
      "Category": "Feedback",
      "Executor": "Emma Lee",
      "Date": "2024-02-15",
      "Status": "Approved",
      "id": "a388"
    },
    {
      "ID": 123854,
      "Sender": "Olivia Martinez",
      "Title": "Bug Report",
      "Text": "Reporting a bug in the system",
      "Category": "Technical",
      "Executor": "Frank Johnson",
      "Date": "2024-02-15",
      "Status": "Closed",
      "id": "3f5c"
    },
    {
      "ID": 123855,
      "Sender": "Michael Davis",
      "Title": "Service Complaint",
      "Text": "Unsatisfactory service experience",
      "Category": "Customer Support",
      "Executor": "Grace Smith",
      "Date": "2024-02-15",
      "Status": "Hold",
      "id": "677a"
    },
    {
      "ID": 123856,
      "Sender": "Sophia Brown",
      "Title": "Question",
      "Text": "Seeking clarification on a feature",
      "Category": "General Inquiry",
      "Executor": "Henry Wilson",
      "Date": "2024-02-15",
      "Status": "Refused",
      "id": "9218"
    }
  ],
  "status": [
    {
      "id": "1",
      "name": "All"
    },
    {
      "id": "2",
      "name": "Opened"
    },
    {
      "id": "3",
      "name": "Execution"
    },
    {
      "id": "4",
      "name": "Closed"
    },
    {
      "id": "5",
      "name": "Hold"
    },
    {
      "id": "6",
      "name": "Approved"
    },
    {
      "id": "7",
      "name": "Refused"
    }
  ]
}